{
    "objb": {
        "b": "b"
    }, 
    "multiple_inheritence": {
        "c": "c", 
        "b": "b", 
        "jsn_inherit": [
            "jsn"
        ], 
        "base": "bar", 
        "sub_object": {
            "three": "3"
        }
    }, 
    "jsn": {
        "bit_shifts": 65792, 
        "array_of_vars": [
            "path/to/data", 
            "hello"
        ], 
        "binary_literal": 19, 
        "base": "foo", 
        "sub_object": {
            "nested_var": 10, 
            "two": "2", 
            "one": "1"
        }, 
        "unquoted_string": "without_whitespace", 
        "unquoted": [
            "strings", 
            "in", 
            "arrays"
        ], 
        "variable_data_path": "path/to/data", 
        "variable_int": 10
    }, 
    "json5": {
        "and_trailing": 8675309.0, 
        "trailing_comma": "in objects", 
        "line_breaks": "Look, Mom! No \\n's!", 
        "single_quotes": "I can use \"doublequotes\" here", 
        "and_in": [
            "arrays"
        ], 
        "unquoted": "and you can quote me on that", 
        "hexadecimal": 912559, 
        "leading_decimal_point": 0.8675309, 
        "positive_sign": 1
    }, 
    "json": {
        "string": "yes", 
        "int": 1, 
        "float": 1.0, 
        "bool": true, 
        "nested_objects": {
            "yes": true
        }, 
        "array": [
            1, 
            2, 
            3
        ], 
        "array_of_objects": [
            {
                "object": 1
            }, 
            {
                "object": 2
            }
        ]
    }, 
    "inheritence": {
        "bit_shifts": 65792, 
        "array_of_vars": [
            "path/to/data", 
            "hello"
        ], 
        "binary_literal": 19, 
        "base": "bar", 
        "sub_object": {
            "one": "1", 
            "three": "3", 
            "two": "2", 
            "nested_var": 10
        }, 
        "unquoted_string": "without_whitespace", 
        "unquoted": [
            "strings", 
            "in", 
            "arrays"
        ], 
        "variable_data_path": "path/to/data", 
        "variable_int": 10
    }, 
    "str_test": ":[{}]'+.,0b0x", 
    "another_file": {
        "jsn": "can import content from other files"
    }
}